reattempt/__init__.py
reattempt/py.typed
reattempt-1.1.4.dist-info/METADATA
reattempt-1.1.4.dist-info/WHEEL
reattempt-1.1.4.dist-info/licenses/LICENSE
reattempt-1.1.4.dist-info/RECORD
