Metadata-Version: 2.4
Name: reattempt
Version: 1.1.4
Summary: Retrying a python function when exceptions are raised
Project-URL: homepage, https://github.com/sylvainmouquet/reattempt
Project-URL: documentation, https://github.com/sylvainmouquet/reattempt
Project-URL: repository, https://github.com/sylvainmouquet/reattempt
Project-URL: changelog, https://github.com/sylvainmouquet/reattempt/releases
Author-email: Sylvain Mouquet <sylvain.mouquet@gmail.com>
License: MIT
License-File: LICENSE
Keywords: async,async gen,decorator,exception handling,exponential backoff,generator,python,retry,sync
Classifier: Development Status :: 5 - Production/Stable
Classifier: Intended Audience :: Developers
Classifier: License :: OSI Approved :: MIT License
Classifier: Programming Language :: Python
Classifier: Programming Language :: Python :: 3
Classifier: Programming Language :: Python :: 3.10
Classifier: Programming Language :: Python :: 3.11
Classifier: Programming Language :: Python :: 3.12
Classifier: Programming Language :: Python :: 3.13
Classifier: Topic :: Software Development :: Libraries :: Python Modules
Requires-Python: >=3.10
